{
  "animals": [
    {
      "id": 1,
      "name": "gdklfgjsldkfjg",
      "breed": "jglksdfjgsdfg",
      "employeeId": 2
    },
    {
      "name": "sdfgsjdfkgljsdfg",
      "breed": "sdfgjsdlfgjskldjfg",
      "id": 2
    },
    {
      "name": "dfgjkdlfjg",
      "breed": "sdfjgkldsfjg",
      "id": 3
    }
  ],
  "employees": [
    {
      "id": 1,
      "name": "Brenda",
      "breed": "Receptionist 48"
    },
    {
      "id": 2,
      "name": "gradi",
      "title": "test"
    },
    {
      "id": 4,
      "name": "Gradi Ellis",
      "breed": "Test 88"
    },
    {
      "name": "fds",
      "title": "fdsa",
      "id": 5
    }
  ],
  "locations": [
    {
      "id": 2,
      "name": "West Nashville",
      "address": "2204 Charlotte Pike"
    },
    {
      "name": "ds",
      "address": "fds",
      "id": 4
    },
    {
      "name": "fds",
      "address": "d",
      "id": 5
    }
  ],
  "owners": [
    {
      "id": 2,
      "name": "Brooke",
      "dogName": "Nellie"
    },
    {
      "id": 3,
      "name": "Kaitlin",
      "dogName": "charlie boy"
    },
    {
      "name": "Gradi Ellis",
      "dogName": "fdsa",
      "id": 4
    }
  ]
}